cdk_simplewebsite_deploy/__init__.py
cdk_simplewebsite_deploy/py.typed
cdk_simplewebsite_deploy/_jsii/__init__.py
cdk_simplewebsite_deploy/_jsii/cdk-simplewebsite-deploy@2.1.8.jsii.tgz
cdk_simplewebsite_deploy-2.1.8.dist-info/LICENSE
cdk_simplewebsite_deploy-2.1.8.dist-info/METADATA
cdk_simplewebsite_deploy-2.1.8.dist-info/WHEEL
cdk_simplewebsite_deploy-2.1.8.dist-info/top_level.txt
cdk_simplewebsite_deploy-2.1.8.dist-info/RECORD
